MANIFEST.in
freeseer-config
freeseer-record
freeseer-reporteditor
freeseer-talkeditor
setup.py
data/48x48-freeseer.png
data/freeseer.desktop
freeseer/__init__.py
freeseer/settings.py
freeseer.egg-info/PKG-INFO
freeseer.egg-info/SOURCES.txt
freeseer.egg-info/dependency_links.txt
freeseer.egg-info/top_level.txt
freeseer/framework/__init__.py
freeseer/framework/area_selector.py
freeseer/framework/config.py
freeseer/framework/database.py
freeseer/framework/failure.py
freeseer/framework/multimedia.py
freeseer/framework/plugin.py
freeseer/framework/presentation.py
freeseer/framework/qt_key_grabber.py
freeseer/framework/rss_parser.py
freeseer/framework/util.py
freeseer/frontend/__init__.py
freeseer/frontend/configtool/AVWidget.py
freeseer/frontend/configtool/ConfigToolWidget.py
freeseer/frontend/configtool/GeneralWidget.py
freeseer/frontend/configtool/PluginLoaderWidget.py
freeseer/frontend/configtool/__init__.py
freeseer/frontend/configtool/configtool.py
freeseer/frontend/controller/Client.py
freeseer/frontend/controller/ClientWidget.py
freeseer/frontend/controller/Server.py
freeseer/frontend/controller/ServerWidget.py
freeseer/frontend/controller/__init__.py
freeseer/frontend/qtcommon/AboutDialog.py
freeseer/frontend/qtcommon/FreeseerApp.py
freeseer/frontend/qtcommon/Resource.py
freeseer/frontend/qtcommon/__init__.py
freeseer/frontend/qtcommon/resource_rc.py
freeseer/frontend/record/RecordingController.py
freeseer/frontend/record/RecordingWidget.py
freeseer/frontend/record/ReportDialog.py
freeseer/frontend/record/__init__.py
freeseer/frontend/record/record.py
freeseer/frontend/reporteditor/ReportEditorWidget.py
freeseer/frontend/reporteditor/__init__.py
freeseer/frontend/reporteditor/reporteditor.py
freeseer/frontend/talkeditor/AddTalkWidget.py
freeseer/frontend/talkeditor/EditorWidget.py
freeseer/frontend/talkeditor/__init__.py
freeseer/frontend/talkeditor/talkeditor.py
freeseer/plugins/audioinput/alsasrc.freeseer-plugin
freeseer/plugins/audioinput/audiotestsrc.freeseer-plugin
freeseer/plugins/audioinput/autoaudiosrc.freeseer-plugin
freeseer/plugins/audioinput/jackaudiosrc.freeseer-plugin
